xara/__init__.py
xara/core.py
xara/fitting.py
xara/iwfs.py
xara/kpi.py
xara/kpo.py
xara_astro-1.0.1.dist-info/METADATA
xara_astro-1.0.1.dist-info/WHEEL
xara_astro-1.0.1.dist-info/licenses/LICENSE.txt
xara_astro-1.0.1.dist-info/RECORD
