Metadata-Version: 2.4
Name: xara-astro
Version: 1.0.1
Summary: A package for eXtreme Angular Resolution Astronomy
Project-URL: Homepage, https://github.com/fmartinache/xara/
Project-URL: Issues, https://github.com/fmartinache/xara/issues
Author-email: Frantz Martinache <frantz.martinache@oca.eu>
License-File: LICENSE.txt
Classifier: License :: OSI Approved :: GNU General Public License v3 (GPLv3)
Classifier: Operating System :: POSIX :: Linux
Classifier: Programming Language :: Python :: 3
Requires-Python: >=3.9
Requires-Dist: astropy
Requires-Dist: matplotlib
Requires-Dist: numpy
Requires-Dist: scipy
Provides-Extra: test
Requires-Dist: pytest; extra == 'test'
Requires-Dist: xaosim; extra == 'test'
